cat2cat/__init__.py
cat2cat/cat2cat.py
cat2cat/cat2cat_ml.py
cat2cat/cat2cat_utils.py
cat2cat/dataclass.py
cat2cat/datasets.py
cat2cat/mappings.py
cat2cat/data/__init__.py
cat2cat/data/occup.pkl
cat2cat/data/occup_small.pkl
cat2cat/data/trans.pkl
cat2cat/data/verticals.pkl
cat2cat-0.1.7.dist-info/licenses/LICENSE
cat2cat-0.1.7.dist-info/METADATA
cat2cat-0.1.7.dist-info/WHEEL
cat2cat-0.1.7.dist-info/top_level.txt
cat2cat-0.1.7.dist-info/RECORD
