Metadata-Version: 2.4
Name: cat2cat
Version: 0.1.7
Summary: Unifying an inconsistently coded categorical variable in a panel/longtitudal dataset.
Author-email: Maciej Nasinski <nasinski.maciej@gmail.com>
License: Apache License 2.0 | file LICENSE
Project-URL: homepage, https://github.com/Polkas/py-cat2cat
Project-URL: documentation, https://py-cat2cat.readthedocs.io/en/latest/
Project-URL: repository, https://github.com/Polkas/py-cat2cat
Project-URL: changelog, https://raw.githubusercontent.com/Polkas/py-cat2cat/main/CHANGELOG.md
Keywords: panel,categorical,longtitudal,inconsistent,cat2cat
Classifier: Development Status :: 3 - Alpha
Classifier: Programming Language :: Python
Classifier: Programming Language :: Python :: 3
Classifier: Programming Language :: Python :: 3.8
Classifier: Programming Language :: Python :: 3.9
Classifier: Programming Language :: Python :: 3.10
Classifier: Programming Language :: Python :: 3.11
Classifier: Programming Language :: Python :: 3.12
Classifier: Programming Language :: Python :: 3.13
Classifier: Programming Language :: Python :: Implementation :: PyPy
Requires-Python: >=3.8
License-File: LICENSE
Requires-Dist: numpy
Requires-Dist: pandas
Requires-Dist: scikit-learn
Requires-Dist: importlib-resources
Provides-Extra: test
Requires-Dist: pytest; extra == "test"
Requires-Dist: pytest-cov; extra == "test"
Requires-Dist: mypy; extra == "test"
Provides-Extra: docs
Requires-Dist: Sphinx; extra == "docs"
Requires-Dist: myst-parser; extra == "docs"
Requires-Dist: sphinx-autoapi; extra == "docs"
Requires-Dist: sphinx-rtd-theme; extra == "docs"
Provides-Extra: build
Requires-Dist: build; extra == "build"
Provides-Extra: benchmark
Requires-Dist: snakeviz; extra == "benchmark"
Provides-Extra: styler
Requires-Dist: flake8; extra == "styler"
Requires-Dist: black; extra == "styler"
Provides-Extra: all
Requires-Dist: cat2cat[benchmark,build,docs,styler,test]; extra == "all"
Dynamic: license-file
